itaxotools/_convphase.cpython-310-x86_64-linux-gnu.so
itaxotools/convphase/__init__.py
itaxotools/convphase/types.py
itaxotools/convphase/scan.py
itaxotools/convphase/__main__.py
itaxotools/convphase/files.py
itaxotools/convphase/phase.py
itaxotools/_convphase/src/convphase.cpp
itaxotools/_convphase/src/python_wrapper.cpp
itaxotools/_convphase/src/main.cpp
itaxotools/_convphase/src/fastaconverter.cpp
itaxotools/_convphase/include/convphase.h
itaxotools/_convphase/include/fastaconverter.h
itaxotools/_convphase/include/python_wrapper.h
itaxotools/_convphase/include/phase.h
itaxotools/_convphase/include/phase_data.h
itaxotools_convphase-0.1.3.dist-info/entry_points.txt
itaxotools_convphase-0.1.3.dist-info/WHEEL
itaxotools_convphase-0.1.3.dist-info/METADATA
itaxotools_convphase-0.1.3.dist-info/RECORD
itaxotools_convphase-0.1.3.dist-info/licenses/LICENSE.txt
